phlower/__init__.py
phlower/dataset.py
phlower/ext.py
phlower/pl.py
phlower/tl.py
phlower/util.py
phlower/external/__init__.py
phlower/external/ddhodge.py
phlower/external/scikit_posthocs.py
phlower/external/stream.py
phlower/external/stream_extra.py
phlower/plot/__init__.py
phlower/plot/adata.py
phlower/plot/persistence.py
phlower/plot/plotting.py
phlower/plot/tree_feature_markers.py
phlower/plot/velocity.py
phlower/tools/__init__.py
phlower/tools/adata_util.py
phlower/tools/aucc.py
phlower/tools/bak.py
phlower/tools/clustering.py
phlower/tools/cumsum_utils.py
phlower/tools/diffusionmap.py
phlower/tools/dimensionreduction.py
phlower/tools/featuretraj.py
phlower/tools/graphconstr.py
phlower/tools/harmonic_pseudo_tree.py
phlower/tools/hodgedecomp.py
phlower/tools/incidence.py
phlower/tools/trajectory.py
phlower/tools/tree_bench.py
phlower/tools/tree_feature_markers.py
phlower/tools/tree_utils.py
phlower/tools/triangulation.py
phlower/tools/viz.py
phlowerpy-0.1.5.dist-info/LICENSE
phlowerpy-0.1.5.dist-info/METADATA
phlowerpy-0.1.5.dist-info/WHEEL
phlowerpy-0.1.5.dist-info/top_level.txt
phlowerpy-0.1.5.dist-info/RECORD
