Metadata-Version: 2.2
Name: phlowerpy
Version: 0.1.5
Summary: hodge decomposition trajectory
Home-page: https://github.com/CostaLab/phlower
Author: Mingbo Cheng
Author-email: chengmingbo@gmail.com
License: BSD 2-clause
Classifier: Development Status :: 1 - Planning
Classifier: Intended Audience :: Science/Research
Classifier: License :: OSI Approved :: BSD License
Classifier: Operating System :: POSIX :: Linux
Classifier: Programming Language :: Python :: 3
Classifier: Programming Language :: Python :: 3.4
Classifier: Programming Language :: Python :: 3.5
Classifier: Programming Language :: Python :: 3.6
Classifier: Programming Language :: Python :: 3.7
Classifier: Programming Language :: Python :: 3.8
Classifier: Programming Language :: Python :: 3.9
Classifier: Programming Language :: Python :: 3.10
Classifier: Programming Language :: Python :: 3.11
Classifier: Programming Language :: Python :: 3.12
License-File: LICENSE
Requires-Dist: numpy>=1.23.5
Requires-Dist: matplotlib>=3.9.1
Requires-Dist: seaborn>=0.12.2
Requires-Dist: networkx>=2.4
Requires-Dist: pydot>=1.4.2
Requires-Dist: igraph>=0.10.5
Requires-Dist: scikit-learn>=1.5.1
Requires-Dist: scipy>=1.11.4
Requires-Dist: pandas>=2.1.3
Requires-Dist: plotly>=5.23.0
Requires-Dist: tqdm>=4.65.0
Requires-Dist: leidenalg>=0.9.1
Requires-Dist: python-louvain>=0.16
Requires-Dist: colorcet>=3.0.1
Requires-Dist: umap-learn>=0.5.5
Requires-Dist: scikit-sparse>=0.4.8
Requires-Dist: scanpy>=1.9.3
Requires-Dist: gudhi>=3.10.1
Requires-Dist: adjustText>=0.8
Requires-Dist: pygraphviz>=1.11
Requires-Dist: magic-impute>=3.0.0
Requires-Dist: anndata>=0.9.2
Dynamic: author
Dynamic: author-email
Dynamic: classifier
Dynamic: description
Dynamic: home-page
Dynamic: license
Dynamic: requires-dist
Dynamic: summary
